{"qas": [{"question": "What team was dominate in the 1960s in La Liga?", "id": "570c4f18fed7b91900d45891", "answers": [{"text": "Real Madrid", "answer_start": 50}], "is_impossible": false}, {"question": "Due to the emergence of Fuste and Rexach, what competition did Barcelona win in 1963?", "id": "570c4f18fed7b91900d45892", "answers": [{"text": "Copa del General\u00edsimo", "answer_start": 280}], "is_impossible": false}, {"question": "What competition did Barcelona win in 1966?", "id": "570c4f18fed7b91900d45893", "answers": [{"text": "Fairs Cup", "answer_start": 318}], "is_impossible": false}, {"question": "Who was present when Barcelona beat Real Madrid in 1968?", "id": "570c4f18fed7b91900d45894", "answers": [{"text": "Franco", "answer_start": 462}], "is_impossible": false}, {"question": "With Franco's dictatorship over, to what did Barcelona change their name ?", "id": "570c4f18fed7b91900d45895", "answers": [{"text": "Futbol Club Barcelona", "answer_start": 633}], "is_impossible": false}], "context": "The 1960s were less successful for the club, with <a0_0>Real Madrid<a0_0/> monopolising La Liga. The completion of the Camp Nou, finished in 1957, meant the club had little money to spend on new players. The 1960s saw the emergence of Josep Maria Fust\u00e9 and Carles Rexach, and the club won the <a1_0>Copa del General\u00edsimo<a1_0/> in 1963 and the <a2_0>Fairs Cup<a2_0/> in 1966. Barcelona restored some pride by beating Real Madrid 1\u20130 in the 1968 Copa del General\u00edsimo final at the Bernab\u00e9u in front of <a3_0>Franco<a3_0/>, with coach Salvador Artigas, a former republican pilot in the civil war. With the end of Franco's dictatorship in 1974, the club changed its official name back to <a4_0>Futbol Club Barcelona<a4_0/> and reverted the crest to its original design, including the original letters once again."}