{"qas": [{"question": "How many Great Lakes form a border with Canada?", "id": "572eb9dbc246551400ce4588", "answers": [{"text": "four", "answer_start": 78}], "is_impossible": false}, {"question": "Which of the Great Lakes is entirely located in US territory?", "id": "572eb9dbc246551400ce4589", "answers": [{"text": "Lake Michigan", "answer_start": 136}], "is_impossible": false}, {"question": "Which major river is located west of the Appalachian mountains?", "id": "572eb9dbc246551400ce458a", "answers": [{"text": "Mississippi River", "answer_start": 348}], "is_impossible": false}, {"question": "What type of land makes up the Ohio and Tennessee valleys?", "id": "572eb9dbc246551400ce458b", "answers": [{"text": "rolling hills and productive farmland", "answer_start": 513}], "is_impossible": false}, {"question": "Which section of the US contains subtropical forests and mangrove wetlands?", "id": "572eb9dbc246551400ce458c", "answers": [{"text": "southeast United States", "answer_start": 194}], "is_impossible": false}, {"plausible_answers": [{"text": "Canada", "answer_start": 123}], "question": "The five Great Lakes formal border with what country?", "id": "5a0f2254d7c85000188645a9", "answers": [], "is_impossible": true}, {"plausible_answers": [{"text": "Lake Michigan", "answer_start": 136}], "question": "Which great Lake is located entirely outside of US territory?", "id": "5a0f2254d7c85000188645aa", "answers": [], "is_impossible": true}, {"plausible_answers": [{"text": "Mississippi River", "answer_start": 348}], "question": "Which major river is located east of the Appalachian Mountains", "id": "5a0f2254d7c85000188645ab", "answers": [], "is_impossible": true}, {"plausible_answers": [{"text": "Ohio River and the Tennessee River", "answer_start": 411}], "question": "What are the two large Western tributaries of the Mississippi River?", "id": "5a0f2254d7c85000188645ac", "answers": [], "is_impossible": true}, {"plausible_answers": [{"text": "The southeast", "answer_start": 190}], "question": "Which section of the US contains tropical forests and mangrove wetlands?", "id": "5a0f2254d7c85000188645ad", "answers": [], "is_impossible": true}], "context": "The five Great Lakes are located in the north-central portion of the country, <a0_0>four<a0_0/> of them forming part of the border with <b5_0>Canada<b5_0/>, only <a1_0><b6_0>Lake Michigan<b6_0/><a1_0/> situated entirely within United States. <b9_0>The <a4_0>southeast<b9_0/> United States<a4_0/> contain subtropical forests and, near the gulf coast, mangrove wetlands, especially in Florida. West of the Appalachians lies the <a2_0><b7_0>Mississippi River<b7_0/><a2_0/> basin and two large eastern tributaries, the <b8_0>Ohio River and the Tennessee River<b8_0/>. The Ohio and Tennessee Valleys and the Midwest consist largely of <a3_0>rolling hills and productive farmland<a3_0/>, stretching south to the Gulf Coast."}