{"qas": [{"question": "Th\u1ebf gi\u1edbi m\u1edbi l\u00e0 g\u00ec D\u1ecbch b\u1ea3n d\u1ecbch ch\u00ednh x\u00e1c nh\u1ea5t?", "id": "57325e6d0fdd8d15006c6a41", "answers": [{"text": "Kinh Th\u00e1nh \u0111\u01b0\u1ee3c s\u1eed d\u1ee5ng r\u1ed9ng r\u00e3i nh\u1ea5t trong th\u1ebf gi\u1edbi n\u00f3i ti\u1ebfng Anh", "answer_start": 54}], "is_impossible": false}, {"question": "\u0110i\u1ec1u g\u00ec l\u00e0m nhi\u1ec1u h\u1ecdc gi\u1ea3 Kinh Th\u00e1nh cho r\u1eb1ng s\u1ef1 kh\u00e1c bi\u1ec7t trong b\u1ea3n d\u1ecbch th\u1ebf gi\u1edbi m\u1edbi l\u00e0 k\u1ebft qu\u1ea3 c\u1ee7a?", "id": "57325e6d0fdd8d15006c6a42", "answers": [{"text": "thi\u00ean v\u1ecb t\u00f4n gi\u00e1o", "answer_start": 409}], "is_impossible": false}, {"question": "BeDuhn l\u00e0m r\u00f5 r\u1eb1ng s\u1ef1 kh\u00e1c bi\u1ec7t th\u1ef1c s\u1ef1 l\u00e0 do c\u00e1i g\u00ec?", "id": "57325e6d0fdd8d15006c6a43", "answers": [{"text": "\u0111\u1ed9 ch\u00ednh x\u00e1c cao h\u01a1n", "answer_start": 503}], "is_impossible": false}, {"question": "NW th\u01b0\u1eddng sai v\u1ec1 ph\u00eda lo\u1ea1i b\u1ea3n d\u1ecbch n\u00e0o?", "id": "57325e6d0fdd8d15006c6a44", "answers": [{"text": "theo ngh\u0129a \u0111en, b\u1ea3o th\u1ee7", "answer_start": 539}], "is_impossible": false}, {"question": "Nh\u1eefng g\u00ec ch\u00e8n v\u00e0o T\u00e2n \u01b0\u1edbc vi ph\u1ea1m ch\u00ednh x\u00e1c \u1ee7ng h\u1ed9 c\u00e1c bi\u1ec3u th\u1ee9c \u0111\u01b0\u1ee3c \u01b0u ti\u00ean m\u1ec7nh gi\u00e1?", "id": "57325e6d0fdd8d15006c6a45", "answers": [{"text": "Jehovah", "answer_start": 655}], "is_impossible": false}, {"plausible_answers": [{"text": "B\u1ea3n d\u1ecbch th\u1ebf gi\u1edbi m\u1edbi", "answer_start": 229}], "question": "Kinh th\u00e1nh n\u00e0o kh\u00f4ng ch\u00e8n \u0110\u1ee9c Gi\u00ea-h\u00f4-va qu\u00e1 th\u01b0\u1eddng xuy\u00ean nh\u01b0 l\u1eddi c\u1ee7a \u0110\u1ee9c Ch\u00faa Tr\u1eddi?", "id": "5ad3eb39604f3c001a3ff70b", "answers": [], "is_impossible": true}, {"plausible_answers": [{"text": "B\u1ea3n d\u1ecbch th\u1ebf gi\u1edbi m\u1edbi", "answer_start": 229}], "question": "\u0110i\u1ec1u g\u00ec \u0111\u01b0\u1ee3c coi l\u00e0 b\u1ea3n d\u1ecbch ch\u00ednh x\u00e1c nh\u1ea5t c\u1ee7a Kinh Th\u00e1nh tr\u00ean th\u1ebf gi\u1edbi trong s\u1ed1 ch\u00edn ch\u00ednh?", "id": "5ad3eb39604f3c001a3ff70c", "answers": [], "is_impossible": true}, {"plausible_answers": [{"text": "\u0110\u1ea1i h\u1ecdc B\u1eafc Arizona", "answer_start": 189}], "question": "Jason BeDuhn, h\u1ecdc gi\u1ea3 Kinh Th\u00e1nh c\u1ee7a tr\u01b0\u1eddng \u0111\u1ea1i h\u1ecdc n\u00e0o l\u1ea5y b\u1eb1ng \u0111\u1ea1i h\u1ecdc c\u1ee7a m\u00ecnh?", "id": "5ad3eb39604f3c001a3ff70d", "answers": [], "is_impossible": true}, {"plausible_answers": [{"text": "Jason", "answer_start": 143}], "question": "Ai l\u00e0 m\u1ed9t trong nh\u1eefng nh\u00e0 v\u0103n T\u00e2n \u01af\u1edbc?", "id": "5ad3eb39604f3c001a3ff70e", "answers": [], "is_impossible": true}], "context": "M\u1eb7t kh\u00e1c, trong nghi\u00ean c\u1ee9u c\u1ee7a \u00f4ng v\u1ec1 ch\u00edn trong s\u1ed1 \" Kinh Th\u00e1nh \u0111\u01b0\u1ee3c s\u1eed d\u1ee5ng r\u1ed9ng r\u00e3i nh\u1ea5t trong th\u1ebf gi\u1edbi n\u00f3i ti\u1ebfng Anh \", H\u1ecdc gi\u1ea3 Kinh Th\u00e1nh Jason BeDuhn, Gi\u00e1o s\u01b0 Nghi\u00ean c\u1ee9u T\u00f4n gi\u00e1o t\u1ea1i \u0110\u1ea1i h\u1ecdc B\u1eafc Arizona, \u0111\u00e3 vi\u1ebft: \u201cThe NW [ B\u1ea3n d\u1ecbch th\u1ebf gi\u1edbi m\u1edbi ] n\u1ed5i l\u00ean l\u00e0 b\u1ea3n d\u1ecbch ch\u00ednh x\u00e1c nh\u1ea5t so s\u00e1nh. \u201dM\u1eb7c d\u00f9 c\u00f4ng ch\u00fang v\u00e0 nhi\u1ec1u h\u1ecdc gi\u1ea3 Kinh Th\u00e1nh cho r\u1eb1ng s\u1ef1 kh\u00e1c bi\u1ec7t trong b\u1ea3n d\u1ecbch th\u1ebf gi\u1edbi m\u1edbi l\u00e0 k\u1ebft qu\u1ea3 c\u1ee7a thi\u00ean v\u1ecb t\u00f4n gi\u00e1o tr\u00ean m\u1ed9t ph\u1ea7n c\u1ee7a d\u1ecbch gi\u1ea3 c\u1ee7a n\u00f3, BeDuhn n\u00f3i: \u201cH\u1ea7u h\u1ebft c\u00e1c kh\u00e1c bi\u1ec7t l\u00e0 do \u0111\u1ed9 ch\u00ednh x\u00e1c cao h\u01a1n c\u1ee7a NW nh\u01b0 m\u1ed9t theo ngh\u0129a \u0111en, b\u1ea3o th\u1ee7 d\u1ecbch c\u00e1c bi\u1ec3u th\u1ee9c g\u1ed1c c\u1ee7a c\u00e1c nh\u00e0 v\u0103n T\u00e2n \u01b0\u1edbc. \u201dTuy nhi\u00ean, \u00f4ng n\u00f3i th\u00eam r\u1eb1ng vi\u1ec7c ch\u00e8n t\u00ean Jehovah trong T\u00e2n \u01af\u1edbc \"\u0111\u1ed9 ch\u00ednh x\u00e1c vi ph\u1ea1m \u1ee7ng h\u1ed9 c\u00e1c bi\u1ec3u th\u1ee9c \u0111\u01b0\u1ee3c \u01b0u ti\u00ean m\u1ec7nh gi\u00e1 cho Th\u01b0\u1ee3ng \u0111\u1ebf\"."}