{"qas": [{"question": "Ai \u0111\u01b0\u1ee3c d\u1ef1a tr\u00ean Swan Inn?", "id": "56dff0b1231d4119001abed1", "answers": [{"text": "Dick Turpin", "answer_start": 23}], "is_impossible": false}, {"question": "Swan Inn n\u1eb1m \u1edf qu\u1eadn n\u00e0o?", "id": "56dff0b1231d4119001abed2", "answers": [{"text": "Buckinghamshire", "answer_start": 90}], "is_impossible": false}, {"question": "T\u00ean c\u1ee7a ch\u1ee7 qu\u00e1n tr\u1ecd t\u1ea1i Spread Eagle v\u00e0o nh\u1eefng n\u0103m 1920 l\u00e0 g\u00ec?", "id": "56dff0b1231d4119001abed3", "answers": [{"text": "John Fothergill", "answer_start": 147}], "is_impossible": false}, {"question": "Nh\u1eadt k\u00fd An Innkeeper \u0111\u01b0\u1ee3c xu\u1ea5t b\u1ea3n v\u00e0o n\u0103m n\u00e0o?", "id": "56dff0b1231d4119001abed4", "answers": [{"text": "1931", "answer_start": 324}], "is_impossible": false}, {"question": "Nh\u00e0 xu\u1ea5t b\u1ea3n n\u00e0o \u0111\u00e3 xu\u1ea5t b\u1ea3n cu\u1ed1n nh\u1eadt k\u00fd c\u1ee7a An Innkeeper?", "id": "56dff0b1231d4119001abed5", "answers": [{"text": "Chatto &amp; Windus", "answer_start": 303}], "is_impossible": false}], "context": "Ng\u01b0\u1eddi \u0111i \u0111\u01b0\u1eddng cao t\u1ed1c Dick Turpin \u0111\u00e3 s\u1eed d\u1ee5ng nh\u00e0 ngh\u1ec9 Swan Inn \u1edf Woughton-on-the-Green \u1edf Buckinghamshire l\u00e0m c\u01a1 s\u1edf c\u1ee7a anh \u1ea5y. V\u00e0o nh\u1eefng n\u0103m 1920 John Fothergill (1876\u20131957) l\u00e0 ch\u1ee7 qu\u00e1n c\u1ee7a Spread Eagle \u1edf \u200b\u200bThame, Berkshire, v\u00e0 xu\u1ea5t b\u1ea3n cu\u1ed1n t\u1ef1 truy\u1ec7n c\u1ee7a m\u00ecnh: Nh\u1eadt k\u00fd c\u1ee7a m\u1ed9t ng\u01b0\u1eddi gi\u1eef s\u00e1ch (London: Chatto &amp; Windus, 1931 ). Trong th\u1eddi gian l\u01b0u tr\u00fa ri\u00eang c\u1ee7a m\u00ecnh, nhi\u1ec1u ng\u01b0\u1eddi n\u1ed5i ti\u1ebfng \u0111\u00e3 \u0111\u1ebfn \u0111\u1ec3 \u1edf l\u1ea1i, ch\u1eb3ng h\u1ea1n nh\u01b0 HG Wells. T\u1ed5ng th\u1ed1ng Hoa K\u1ef3 George W. Bush ho\u00e0n th\u00e0nh tham v\u1ecdng tr\u1ecdn \u0111\u1eddi c\u1ee7a m\u00ecnh khi \u0111\u1ebfn th\u0103m m\u1ed9t &#39;qu\u00e1n r\u01b0\u1ee3u Anh ch\u00ednh th\u1ed1ng&#39; trong chuy\u1ebfn th\u0103m nh\u00e0 n\u01b0\u1edbc th\u00e1ng 11 n\u0103m 2003 c\u1ee7a \u00f4ng t\u1edbi Anh khi \u00f4ng \u0103n tr\u01b0a v\u00e0 m\u1ed9t l\u00edt bia kh\u00f4ng c\u1ed3n (Bush l\u00e0 m\u1ed9t teetotaler) v\u1edbi Th\u1ee7 t\u01b0\u1edbng Anh Tony Blair t\u1ea1i qu\u00e1n r\u01b0\u1ee3u Dun Cow \u1edf Sedgefield, County Durham trong khu v\u1ef1c b\u1ea7u c\u1eed c\u1ee7a Blair. C\u00f3 kho\u1ea3ng 53.500 ng\u00f4i nh\u00e0 c\u00f4ng c\u1ed9ng trong n\u0103m 2009 t\u1ea1i V\u01b0\u01a1ng qu\u1ed1c Anh. Con s\u1ed1 n\u00e0y \u0111\u00e3 gi\u1ea3m d\u1ea7n m\u1ed7i n\u0103m, do \u0111\u00f3 g\u1ea7n m\u1ed9t n\u1eeda s\u1ed1 l\u00e0ng nh\u1ecf kh\u00f4ng c\u00f2n c\u00f3 qu\u00e1n r\u01b0\u1ee3u \u0111\u1ecba ph\u01b0\u01a1ng n\u1eefa."}