{"qas": [{"question": "The new Iranian government following the Shah's downfall dealt with the Kurdish rebellion in what year?", "id": "573015d6947a6a140053d0a2", "answers": [{"text": "1979", "answer_start": 75}], "is_impossible": false}, {"question": "How did the new Iranian government handle the rebellions and uprisings following their rise to power?", "id": "573015d6947a6a140053d0a3", "answers": [{"text": "in a violent manner", "answer_start": 263}], "is_impossible": false}, {"question": "The new Iranian government purged itself of what political opposition?", "id": "573015d6947a6a140053d0a4", "answers": [{"text": "non-Islamist", "answer_start": 366}], "is_impossible": false}, {"question": "What happened to the nationalists and Marxists that had helped the Islamic ruling government to depose the Shah?", "id": "573015d6947a6a140053d0a5", "answers": [{"text": "were executed", "answer_start": 518}], "is_impossible": false}], "context": "Cu\u1ed9c n\u1ed5i d\u1eady to\u00e0n qu\u1ed1c ngay l\u1eadp t\u1ee9c ch\u1ed1ng l\u1ea1i ch\u00ednh ph\u1ee7 m\u1edbi b\u1eaft \u0111\u1ea7u b\u1edfi <a0_0> 1979 <a0_0/> Cu\u1ed9c n\u1ed5i d\u1eady c\u1ee7a ng\u01b0\u1eddi Kurd v\u1edbi cu\u1ed9c n\u1ed5i d\u1eady Khuzestan, c\u00f9ng v\u1edbi nh\u1eefng cu\u1ed9c n\u1ed5i lo\u1ea1n \u1edf t\u1ec9nh Sistan v\u00e0 Baluchestan v\u00e0 c\u00e1c khu v\u1ef1c kh\u00e1c. Trong v\u00e0i n\u0103m t\u1edbi, nh\u1eefng cu\u1ed9c n\u1ed5i lo\u1ea1n n\u00e0y \u0111\u00e3 b\u1ecb chinh ph\u1ee5c <a1_0> m\u1ed9t c\u00e1ch b\u1ea1o l\u1ef1c <a1_0/> b\u1edfi ch\u00ednh ph\u1ee7 H\u1ed3i gi\u00e1o m\u1edbi. Ch\u00ednh ph\u1ee7 m\u1edbi \u0111i v\u1ec1 vi\u1ec7c thanh t\u1ea9y ch\u00ednh n\u00f3 <a2_0> ng\u01b0\u1eddi kh\u00f4ng theo \u0111\u1ea1o H\u1ed3i <a2_0/> \u0111\u1ed1i l\u1eadp ch\u00ednh tr\u1ecb. M\u1eb7c d\u00f9 c\u1ea3 hai ch\u1ee7 ngh\u0129a d\u00e2n t\u1ed9c v\u00e0 ch\u1ee7 ngh\u0129a M\u00e1c \u0111\u00e3 b\u01b0\u1edbc \u0111\u1ea7u tham gia v\u1edbi nh\u1eefng ng\u01b0\u1eddi H\u1ed3i gi\u00e1o \u0111\u1ec3 l\u1eadt \u0111\u1ed5 Shah, h\u00e0ng ch\u1ee5c ng\u00e0n <a3_0> \u0110\u00e3 \u0111\u01b0\u1ee3c th\u1ef1c hi\u1ec7n <a3_0/> b\u1edfi ch\u00ednh ph\u1ee7 H\u1ed3i gi\u00e1o sau \u0111\u00f3."}