{"qas": [{"question": "Local Southampton football leagues have what day of the week in their names?", "id": "56f8c2519e9bad19000a0446", "answers": [{"text": "Sunday", "answer_start": 14}], "is_impossible": false}, {"question": "How many local Sunday football leagues does Southampton have? ", "id": "56f8c2519e9bad19000a0447", "answers": [{"text": "two", "answer_start": 4}], "is_impossible": false}, {"question": "What's the name of the local league with \"City\" in its name?", "id": "56f8c2519e9bad19000a0448", "answers": [{"text": "City of Southampton Sunday Football League", "answer_start": 61}], "is_impossible": false}, {"question": "What's the name of the the local league with \"District\" in its name?", "id": "56f8c2519e9bad19000a0449", "answers": [{"text": "Southampton and District Sunday Football League", "answer_start": 112}], "is_impossible": false}], "context": "The <a1_0>two<a1_0/> local <a0_0>Sunday<a0_0/> Leagues in the Southampton area are the <a2_0>City of Southampton Sunday Football League<a2_0/> and the <a3_0>Southampton and District Sunday Football League<a3_0/>."}