{"qas": [{"question": "C\u00f3 bao nhi\u00eau h\u1ecdc sinh theo h\u1ecdc t\u1ea1i tr\u01b0\u1eddng BYU?", "id": "572643ee1125e71900ae1914", "answers": [{"text": "29.672", "answer_start": 395}], "is_impossible": false}, {"question": "C\u00f3 bao nhi\u00eau h\u1ecdc sinh c\u0169ng l\u00e0 th\u00e0nh vi\u00ean c\u1ee7a Gi\u00e1o H\u1ed9i C\u00e1c Th\u00e1nh H\u1eefu Ng\u00e0y Sau?", "id": "572643ee1125e71900ae1915", "answers": [{"text": "99%", "answer_start": 444}], "is_impossible": false}, {"question": "Ph\u1ea7n n\u00e0o c\u1ee7a h\u1ecdc sinh l\u00e0 c\u01b0 d\u00e2n Utah b\u1ea3n x\u1ee9?", "id": "572643ee1125e71900ae1916", "answers": [{"text": "m\u1ed9t ph\u1ea7n ba", "answer_start": 500}], "is_impossible": false}, {"question": "\u0110\u1ea1i h\u1ecdc Brigham Young \u1edf \u0111\u00e2u?", "id": "572643ee1125e71900ae1917", "answers": [{"text": "Provo, Utah", "answer_start": 118}], "is_impossible": false}, {"question": "C\u00f3 bao nhi\u00eau sinh vi\u00ean hi\u1ec7n \u0111ang theo h\u1ecdc t\u1ea1i tr\u01b0\u1eddng BYU?", "id": "572678ca5951b619008f73ad", "answers": [{"text": "29.672", "answer_start": 395}], "is_impossible": false}, {"question": "Khu\u00f4n vi\u00ean ch\u00ednh c\u1ee7a BYU \u1edf \u0111\u00e2u?", "id": "572678ca5951b619008f73ae", "answers": [{"text": "Provo, Utah", "answer_start": 118}], "is_impossible": false}, {"question": "Th\u1ee9 h\u1ea1ng c\u1ee7a BYU trong s\u1ed1 c\u00e1c tr\u01b0\u1eddng \u0111\u1ea1i h\u1ecdc t\u01b0 l\u00e0 g\u00ec?", "id": "572678ca5951b619008f73af", "answers": [{"text": "th\u1ee9 ba", "answer_start": 347}], "is_impossible": false}, {"question": "C\u00f3 bao nhi\u00eau sinh vi\u00ean c\u1ee7a BYU l\u00e0 c\u01b0 d\u00e2n Utah b\u1ea3n x\u1ee9?", "id": "572678ca5951b619008f73b0", "answers": [{"text": "m\u1ed9t ph\u1ea7n ba", "answer_start": 500}], "is_impossible": false}, {"question": "T\u1ef7 l\u1ec7 ph\u1ea7n tr\u0103m h\u1ecdc sinh c\u1ee7a BYU \u0111\u1ebfn t\u1eeb Utah l\u00e0 bao nhi\u00eau?", "id": "572823673acd2414000df573", "answers": [{"text": "m\u1ed9t ph\u1ea7n ba", "answer_start": 500}], "is_impossible": false}, {"question": "T\u1ef7 l\u1ec7 ph\u1ea7n tr\u0103m h\u1ecdc sinh c\u1ee7a BYU l\u00e0 th\u00e0nh vi\u00ean c\u1ee7a Gi\u00e1o H\u1ed9i LDS?", "id": "572823673acd2414000df574", "answers": [{"text": "X\u1ea5p x\u1ec9 99%", "answer_start": 437}], "is_impossible": false}, {"question": "Quy m\u00f4 c\u1ee7a BYU \u0111\u01b0\u1ee3c x\u1ebfp h\u1ea1ng nh\u01b0 th\u1ebf n\u00e0o trong s\u1ed1 t\u1ea5t c\u1ea3 c\u00e1c tr\u01b0\u1eddng \u0111\u1ea1i h\u1ecdc t\u01b0 th\u1ee5c \u1edf M\u1ef9?", "id": "572823673acd2414000df575", "answers": [{"text": "c\u00e1c th\u1ee9 ba l\u1edbn nh\u1ea5t", "answer_start": 343}], "is_impossible": false}, {"question": "LDS hi\u1ec7n nh\u1eefng g\u00ec \u0111\u1ee9ng cho?", "id": "572823673acd2414000df576", "answers": [{"text": "Gi\u00e1o H\u1ed9i C\u00e1c Th\u00e1nh H\u1eefu Ng\u00e0y Sau c\u1ee7a Ch\u00faa Gi\u00ea Su Ky T\u00f4", "answer_start": 171}], "is_impossible": false}, {"question": "Ai s\u1edf h\u1eefu v\u00e0 \u0111i\u1ec1u h\u00e0nh \u0110\u1ea1i h\u1ecdc Brigham?", "id": "572823673acd2414000df577", "answers": [{"text": "Gi\u00e1o H\u1ed9i C\u00e1c Th\u00e1nh H\u1eefu Ng\u00e0y Sau c\u1ee7a Ch\u00faa Gi\u00ea Su Ky T\u00f4", "answer_start": 171}], "is_impossible": false}, {"plausible_answers": [{"text": "\u0110\u1ea1i h\u1ecdc Brigham Young", "answer_start": 0}], "question": "Tr\u01b0\u1eddng \u0111\u1ea1i h\u1ecdc n\u00e0o \u0111\u01b0\u1ee3c g\u1ecdi l\u00e0 MUA?", "id": "5ace925632bba1001ae4aa75", "answers": [], "is_impossible": true}, {"plausible_answers": [{"text": "Gi\u00e1o H\u1ed9i C\u00e1c Th\u00e1nh H\u1eefu Ng\u00e0y Sau c\u1ee7a Ch\u00faa Gi\u00ea Su Ky T\u00f4", "answer_start": 171}], "question": "Gi\u00e1o h\u1ed9i n\u00e0o \u0111\u01b0\u1ee3c vi\u1ebft t\u1eaft l\u00e0 LSD?", "id": "5ace925632bba1001ae4aa76", "answers": [], "is_impossible": true}, {"plausible_answers": [{"text": "sinh vi\u00ean trong khu\u00f4n vi\u00ean tr\u01b0\u1eddng", "answer_start": 402}], "question": "BYU c\u00f3 29.762 c\u00e1i g\u00ec?", "id": "5ace925632bba1001ae4aa77", "answers": [], "is_impossible": true}, {"plausible_answers": [{"text": "\u0110\u1ea1i h\u1ecdc Brigham Young", "answer_start": 0}], "question": "\u0110\u1ea1i h\u1ecdc t\u01b0 th\u1ee5c l\u1edbn nh\u1ea5t \u1edf Hoa K\u1ef3 l\u00e0 g\u00ec?", "id": "5ace925632bba1001ae4aa78", "answers": [], "is_impossible": true}, {"plausible_answers": [{"text": "\u0110\u1ea1i h\u1ecdc Brigham Young", "answer_start": 0}], "question": "\u0110\u1ea1i h\u1ecdc t\u00f4n gi\u00e1o l\u1edbn th\u1ee9 ba \u1edf Hoa K\u1ef3 l\u00e0 g\u00ec?", "id": "5ace925632bba1001ae4aa79", "answers": [], "is_impossible": true}], "context": " \u0110\u1ea1i h\u1ecdc Brigham Young (th\u01b0\u1eddng \u0111\u01b0\u1ee3c g\u1ecdi l\u00e0 BYU ho\u1eb7c, th\u00f4ng t\u1ee5c, The Y) l\u00e0 m\u1ed9t tr\u01b0\u1eddng \u0111\u1ea1i h\u1ecdc nghi\u00ean c\u1ee9u t\u01b0 nh\u00e2n n\u1eb1m \u1edf Provo, Utah, Hoa K\u1ef3. N\u00f3 \u0111\u01b0\u1ee3c s\u1edf h\u1eefu v\u00e0 \u0111i\u1ec1u h\u00e0nh b\u1edfi Gi\u00e1o H\u1ed9i C\u00e1c Th\u00e1nh H\u1eefu Ng\u00e0y Sau c\u1ee7a Ch\u00faa Gi\u00ea Su Ky T\u00f4 (LDS Church), v\u00e0, ngo\u1ea1i tr\u1eeb h\u1ecdc sinh tr\u1ef1c tuy\u1ebfn, l\u00e0 tr\u01b0\u1eddng \u0111\u1ea1i h\u1ecdc l\u1edbn nh\u1ea5t c\u1ee7a b\u1ea5t k\u1ef3 tr\u01b0\u1eddng \u0111\u1ea1i h\u1ecdc t\u00f4n gi\u00e1o n\u00e0o v\u00e0 c\u00e1c th\u1ee9 ba l\u1edbn nh\u1ea5t tr\u01b0\u1eddng \u0111\u1ea1i h\u1ecdc t\u01b0 \u1edf Hoa K\u1ef3, v\u1edbi 29.672 sinh vi\u00ean trong khu\u00f4n vi\u00ean tr\u01b0\u1eddng. X\u1ea5p x\u1ec9 99% c\u1ee7a c\u00e1c h\u1ecdc sinh l\u00e0 th\u00e0nh vi\u00ean c\u1ee7a Gi\u00e1o H\u1ed9i LDS, v\u00e0 m\u1ed9t ph\u1ea7n ba c\u1ee7a c\u00e1c sinh vi\u00ean Hoa K\u1ef3 \u0111\u1ebfn t\u1eeb Utah."}