{"qas": [{"question": "Popper \u0111\u00e3 nh\u1eadn \u0111\u01b0\u1ee3c gi\u1ea3i th\u01b0\u1edfng n\u00e0o t\u1eeb Hi\u1ec7p h\u1ed9i Khoa h\u1ecdc Ch\u00ednh tr\u1ecb M\u1ef9?", "id": "5728a1ddff5b5019007da35e", "answers": [{"text": "Lippincott Award", "answer_start": 63}], "is_impossible": false}, {"question": "\u00c1o \u0111\u01b0\u1ee3c c\u00f4ng nh\u1eadn cho Popper v\u00e0o n\u0103m 1986?", "id": "5728a1ddff5b5019007da35f", "answers": [{"text": "Grand Decoration of Honour in Gold for Services to the Republic of Austria", "answer_start": 416}], "is_impossible": false}, {"question": "Ai \u0111\u00e3 trao cho Popper gi\u1ea3i th\u01b0\u1edfng Nh\u00e2n v\u0103n Laureate c\u1ee7a n\u00f3?", "id": "5728a1ddff5b5019007da360", "answers": [{"text": "International Academy of Humanism", "answer_start": 692}], "is_impossible": false}, {"question": "Qu\u1ed1c v\u01b0\u01a1ng Anh n\u00e0o \u0111\u00e3 hi\u1ec7p s\u0129 Popper?", "id": "5728a1ddff5b5019007da361", "answers": [{"text": "Queen Elizabeth II", "answer_start": 746}], "is_impossible": false}, {"question": "Tr\u01b0\u1eddng \u0111\u1ea1i h\u1ecdc trung t\u00e2m ch\u00e2u \u00c2u n\u00e0o \u0111\u00e3 l\u00e0m cho Popper tr\u1edf th\u00e0nh m\u1ed9t \u0111\u1ed3ng nghi\u1ec7p?", "id": "5728a1ddff5b5019007da362", "answers": [{"text": "Charles University, Prague", "answer_start": 364}], "is_impossible": false}, {"plausible_answers": [{"text": "1965", "answer_start": 768}], "question": "Khi n\u00e0o Popper \u0111\u01b0\u1ee3c vua George phong t\u01b0\u1edbc hi\u1ec7p s\u0129?", "id": "5ad236bfd7d075001a42881a", "answers": [], "is_impossible": true}, {"plausible_answers": [{"text": "Sonning Prize", "answer_start": 131}], "question": "Popper vinh d\u1ef1 kh\u00f4ng bao gi\u1edd th\u1eafng?", "id": "5ad236bfd7d075001a42881b", "answers": [], "is_impossible": true}, {"plausible_answers": [{"text": "Grand Decoration of Honour in Gold", "answer_start": 416}], "question": "Nga \u0111\u00e3 g\u1eedi gi\u1ea3i th\u01b0\u1edfng n\u00e0o cho Popper?", "id": "5ad236bfd7d075001a42881c", "answers": [], "is_impossible": true}, {"plausible_answers": [{"text": "1976", "answer_start": 823}], "question": "Khi \u0111\u01b0\u1ee3c Popper n\u00e9m ra kh\u1ecfi H\u1ed9i Ho\u00e0ng gia?", "id": "5ad236bfd7d075001a42881d", "answers": [], "is_impossible": true}, {"plausible_answers": [{"text": "Insignia of a Companion of Honour", "answer_start": 854}], "question": "Popper \u0111\u00e3 thua gi\u1ea3i n\u00e0o v\u00e0o n\u0103m 1982?", "id": "5ad236bfd7d075001a42881e", "answers": [], "is_impossible": true}], "context": "Popper \u0111\u00e3 gi\u00e0nh \u0111\u01b0\u1ee3c nhi\u1ec1u gi\u1ea3i th\u01b0\u1edfng v\u00e0 danh d\u1ef1 trong l\u0129nh v\u1ef1c c\u1ee7a m\u00ecnh, bao g\u1ed3m c\u1ea3 <a0_0> Gi\u1ea3i th\u01b0\u1edfng Lippincott <a0_0/> c\u1ee7a Hi\u1ec7p h\u1ed9i Khoa h\u1ecdc Ch\u00ednh tr\u1ecb M\u1ef9, <b6_0> Gi\u1ea3i Sonning <b6_0/> , Huy ch\u01b0\u01a1ng H\u00f2a b\u00ecnh Otto Hahn c\u1ee7a Hi\u1ec7p h\u1ed9i Li\u00ean h\u1ee3p qu\u1ed1c \u0110\u1ee9c t\u1ea1i Berlin v\u00e0 h\u1ecdc b\u1ed5ng t\u1ea1i H\u1ed9i Ho\u00e0ng gia, H\u1ecdc vi\u1ec7n Anh, Tr\u01b0\u1eddng Kinh t\u1ebf Lu\u00e2n \u0110\u00f4n, Cao \u0111\u1eb3ng King London, Cao \u0111\u1eb3ng Darwin, Cambridge v\u00e0 <a4_0> \u0110\u1ea1i h\u1ecdc Charles, Prague <a4_0/> . \u00c1o trao cho anh ta <a1_0><b7_0> Trang tr\u00ed danh d\u1ef1 l\u1edbn b\u1eb1ng v\u00e0ng <b7_0/> D\u1ecbch v\u1ee5 cho C\u1ed9ng h\u00f2a \u00c1o <a1_0/> v\u00e0o n\u0103m 1986, v\u00e0 C\u1ed9ng h\u00f2a Li\u00ean bang \u0110\u1ee9c, H\u1ed9i Ch\u1eef th\u1eadp l\u1edbn c\u1ee7a n\u00f3 v\u1edbi Ng\u00f4i sao v\u00e0 Sash of the Order of Merit, v\u00e0 l\u1edbp h\u00f2a b\u00ecnh c\u1ee7a Order Pour le M\u00e9rite. \u00d4ng \u0111\u00e3 nh\u1eadn \u0111\u01b0\u1ee3c gi\u1ea3i th\u01b0\u1edfng Nh\u00e2n v\u0103n Laureate t\u1eeb <a2_0> H\u1ecdc vi\u1ec7n Nh\u00e2n v\u0103n Qu\u1ed1c t\u1ebf <a2_0/> . \u00d4ng \u0111\u01b0\u1ee3c phong t\u01b0\u1edbc hi\u1ec7p s\u0129 <a3_0> N\u1eef ho\u00e0ng Elizabeth II <a3_0/> trong <b5_0> 1965 <b5_0/> , v\u00e0 \u0111\u01b0\u1ee3c b\u1ea7u l\u00e0 U\u1ef7 vi\u00ean c\u1ee7a H\u1ed9i Ho\u00e0ng gia t\u1ea1i <b8_0> 1976 <b8_0/> . Anh ta \u0111\u00e3 \u0111\u01b0\u1ee3c \u0111\u1ea7u t\u01b0 v\u1edbi <b9_0> Insignia c\u1ee7a m\u1ed9t Companion of Honor <b9_0/> v\u00e0o n\u0103m 1982."}