{"qas": [{"question": "Which school is located on Cabrini Boulevard?", "id": "56f978fb9b226e1400dd1484", "answers": [{"text": "P.S. 187", "answer_start": 175}], "is_impossible": false}, {"question": "On what street is the Dombrov Shtiebel?", "id": "56f978fb9b226e1400dd1485", "answers": [{"text": "187th Street", "answer_start": 25}], "is_impossible": false}, {"question": "Which University has a campus on 187th Street?", "id": "56f978fb9b226e1400dd1486", "answers": [{"text": "Yeshiva University", "answer_start": 120}], "is_impossible": false}, {"question": "Cabrini Boulevard is just north of what street?", "id": "56f978fb9b226e1400dd1487", "answers": [{"text": "187th Street", "answer_start": 245}], "is_impossible": false}, {"question": "On what street is the Mount Sinai Jewish Center?", "id": "56f978fb9b226e1400dd1488", "answers": [{"text": "187th Street", "answer_start": 25}], "is_impossible": false}], "context": "Nhi\u1ec1u t\u1ed5 ch\u1ee9c tr\u00ean <a1_0><a4_0> \u0110\u01b0\u1eddng 187th <a4_0/><a1_0/> bao g\u1ed3m Trung t\u00e2m Do Th\u00e1i Mount Sinai, Dombrov Shtiebel, v\u00e0 khu h\u1ecdc x\u00e1 <a2_0> \u0110\u1ea1i h\u1ecdc Yeshiva <a2_0/> . Tr\u01b0\u1eddng ti\u1ec3u h\u1ecdc c\u00f4ng l\u1eadp \u0111\u1ecba ph\u01b0\u01a1ng <a0_0> PS 187 <a0_0/> n\u1eb1m tr\u00ean \u0110\u1ea1i l\u1ed9 Cabrini, ngay ph\u00eda b\u1eafc c\u1ee7a <a3_0> \u0110\u01b0\u1eddng 187th <a3_0/>"}