{"qas": [{"question": "When did the U.N. vote to adopt the Sustainable Development Goals?", "id": "56df4c618bc80c19004e4a2d", "answers": [{"text": "2015", "answer_start": 13}], "is_impossible": false}, {"question": "How many countries adopted the Sustainable Development Goals?", "id": "56df4c618bc80c19004e4a2e", "answers": [{"text": "193", "answer_start": 23}], "is_impossible": false}, {"question": "How many Sustainable Development Goals are there?", "id": "56df4c618bc80c19004e4a30", "answers": [{"text": "17", "answer_start": 127}], "is_impossible": false}, {"question": "The Sustainable Development Goals are intended to change the world over what time period?", "id": "56df4c618bc80c19004e4a31", "answers": [{"text": "15 years", "answer_start": 180}], "is_impossible": false}, {"plausible_answers": [{"text": "193", "answer_start": 23}], "question": "How many member states voted against Sustainable Development Goals?", "id": "5a297a7203c0e7001a3e179c", "answers": [], "is_impossible": true}, {"plausible_answers": [{"text": "15", "answer_start": 180}], "question": "How many years did it take to form the goals?", "id": "5a297a7203c0e7001a3e179d", "answers": [], "is_impossible": true}, {"plausible_answers": [{"text": "Sustainable Development Goals", "answer_start": 87}], "question": "What goals aimed at keeping things the same in the world?", "id": "5a297a7203c0e7001a3e179e", "answers": [], "is_impossible": true}, {"plausible_answers": [{"text": "Sustainable Development Goals", "answer_start": 87}], "question": "Which goals were designed to increase poverty?", "id": "5a297a7203c0e7001a3e179f", "answers": [], "is_impossible": true}, {"plausible_answers": [{"text": "environmental destruction", "answer_start": 291}], "question": "What was considered unimportant to the UN?", "id": "5a297a7203c0e7001a3e17a0", "answers": [], "is_impossible": true}], "context": "Trong th\u00e1ng Ch\u00edn <a0_0> 2015 <a0_0/> , c\u00e1c <a1_0><b4_0> 193 <b4_0/><a1_0/> c\u00e1c qu\u1ed1c gia th\u00e0nh vi\u00ean c\u1ee7a Li\u00ean Hi\u1ec7p Qu\u1ed1c nh\u1ea5t tr\u00ed th\u00f4ng qua <b6_0><b7_0> M\u1ee5c ti\u00eau ph\u00e1t tri\u1ec3n b\u1ec1n v\u1eefng <b7_0/><b6_0/> , m\u1ed9t t\u1eadp h\u1ee3p c\u00e1c <a2_0> 17 <a2_0/> m\u1ee5c ti\u00eau nh\u1eb1m bi\u1ebfn \u0111\u1ed5i th\u1ebf gi\u1edbi trong t\u01b0\u01a1ng lai <a3_0><b5_0> 15 <b5_0/> n\u0103m <a3_0/> . C\u00e1c m\u1ee5c ti\u00eau n\u00e0y \u0111\u01b0\u1ee3c thi\u1ebft k\u1ebf \u0111\u1ec3 x\u00f3a \u0111\u00f3i gi\u1ea3m ngh\u00e8o, ph\u00e2n bi\u1ec7t \u0111\u1ed1i x\u1eed, l\u1ea1m d\u1ee5ng v\u00e0 c\u00f3 th\u1ec3 ng\u0103n ng\u1eeba t\u1eed vong, \u0111\u1ecba ch\u1ec9 <b8_0> ph\u00e1 h\u1ee7y m\u00f4i tr\u01b0\u1eddng <b8_0/> v\u00e0 m\u1edf ra m\u1ed9t k\u1ef7 nguy\u00ean ph\u00e1t tri\u1ec3n cho t\u1ea5t c\u1ea3 m\u1ecdi ng\u01b0\u1eddi, \u1edf m\u1ecdi n\u01a1i."}