{"qas": [{"question": "When did the Normandy invasion occur?", "id": "57324c70e17f3d140042280f", "answers": [{"text": "June 6, 1944", "answer_start": 31}], "is_impossible": false}, {"question": "How long after the Normandy invasion did the landings in Southern France occur?", "id": "57324c70e17f3d1400422810", "answers": [{"text": "month", "answer_start": 75}], "is_impossible": false}, {"question": "When did the war in Europe end?", "id": "57324c70e17f3d1400422811", "answers": [{"text": "May 8, 1945", "answer_start": 398}], "is_impossible": false}, {"question": "How many divisions involved in the Allied invasion of Europe did Eisenhower visit?", "id": "57324c70e17f3d1400422812", "answers": [{"text": "every", "answer_start": 799}], "is_impossible": false}, {"question": "After what possible event would the speech called one of the greatest in history have been delivered?", "id": "57324c70e17f3d1400422813", "answers": [{"text": "if the invasion failed", "answer_start": 934}], "is_impossible": false}], "context": "The D-Day Normandy landings on <a0_0>June 6, 1944<a0_0/>, were costly but successful. A <a1_0>month<a1_0/> later, the invasion of Southern France took place, and control of forces in the southern invasion passed from the AFHQ to the SHAEF. Many prematurely considered that victory in Europe would come by summer's end\u2014however the Germans did not capitulate for almost a year. From then until the end of the war in Europe on <a2_0>May 8, 1945<a2_0/>, Eisenhower, through SHAEF, commanded all Allied forces, and through his command of ETOUSA had administrative command of all U.S. forces on the Western Front north of the Alps. He was ever mindful of the inevitable loss of life and suffering that would be experienced on an individual level by the troops under his command and their families. This prompted him to make a point of visiting <a3_0>every<a3_0/> division involved in the invasion. Eisenhower's sense of responsibility was underscored by his draft of a statement to be issued <a4_0>if the invasion failed<a4_0/>. It has been called one of the great speeches of history:"}